opsys_eol_ps/__init__.py
opsys_eol_ps/eol_ps.py
opsys_eol_ps-0.0.5.dist-info/LICENSE
opsys_eol_ps-0.0.5.dist-info/METADATA
opsys_eol_ps-0.0.5.dist-info/WHEEL
opsys_eol_ps-0.0.5.dist-info/top_level.txt
opsys_eol_ps-0.0.5.dist-info/RECORD
