Metadata-Version: 2.1
Name: opsys-eol-ps
Version: 0.0.5
Summary: python package for the eol power supply
Home-page: https://bitbucket.org/opsys_tech/opsys_eol_ps/src/master/
Download-URL: https://bitbucket.org/opsys_tech/opsys_eol_ps/src/master/
Author: nerya.lifshitz
Author-email: nerya.lifshitz@opsys-tech.com
License-File: LICENSE
